Metadata-Version: 2.4
Name: llama-index-vector-stores-mariadb
Version: 0.4.1
Summary: llama-index vector_stores mariadb integration
Author-email: Kalin Arsov <kalin@skysql.com>, Vishal Rao <vishal@skysql.com>
License-Expression: MIT
License-File: LICENSE
Requires-Python: <4.0,>=3.9
Requires-Dist: llama-index-core<0.15,>=0.13.0
Requires-Dist: pymysql<2,>=1.1.1
Requires-Dist: sqlalchemy<2.1,>=2.0
